suno/__init__.py
suno/__main__.py
suno/api.py
suno/cli.py
suno/suno.py
suno_api-0.1.2.dist-info/LICENSE
suno_api-0.1.2.dist-info/METADATA
suno_api-0.1.2.dist-info/WHEEL
suno_api-0.1.2.dist-info/entry_points.txt
suno_api-0.1.2.dist-info/RECORD
