Metadata-Version: 2.1
Name: suno-api
Version: 0.1.2
Summary: Unofficial Python library for Suno AI API: make a song with Suno using v3 🥳
Home-page: https://pypi.org/project/suno-api
License: BSD-3-Clause
Author: Yi ZHANG
Author-email: yizhang.dev@gmail.com
Requires-Python: >=3.12,<4.0
Classifier: License :: OSI Approved :: BSD License
Classifier: Programming Language :: Python :: 3
Classifier: Programming Language :: Python :: 3.12
Requires-Dist: curl_cffi (>=0.6.1,<0.7.0)
Requires-Dist: fastapi (>=0.110.0,<0.111.0)
Requires-Dist: typer[all] (>=0.10.0,<0.11.0)
Requires-Dist: uvicorn[standard] (>=0.29.0,<0.30.0)
Project-URL: Documentation, https://suno-api.readthedocs.io/en/latest/
Project-URL: Repository, https://github.com/imyizhang/suno-api
